hostwinds/__init__.py
hostwinds/alert.py
hostwinds/entry/__init__.py
hostwinds/entry/alert_command.py
hostwinds/hostwinds.py
hostwinds_tool-1.0.0.dist-info/entry_points.txt
hostwinds_tool-1.0.0.dist-info/WHEEL
hostwinds_tool-1.0.0.dist-info/METADATA
hostwinds_tool-1.0.0.dist-info/RECORD
