Metadata-Version: 2.1
Name: hostwinds-tool
Version: 1.0.0
Summary: A hostwinds api toolset.
License: MIT
Author: Ray
Author-email: linxray@gmail.com
Requires-Python: >=3.6,<4.0
Classifier: License :: OSI Approved :: MIT License
Classifier: Programming Language :: Python :: 3
Classifier: Programming Language :: Python :: 3.6
Classifier: Programming Language :: Python :: 3.7
Classifier: Programming Language :: Python :: 3.8
Requires-Dist: requests (>=2.22.0,<3.0.0)
